{
	"pm":"POST",
	"ph":{
		"appTypeId":"2",
		"language":"CN",
		"version":"5.67.0",
		"authorization":"f1997f90a9465d0d1df62e92ef3d609f",
		"countrycode":"CN",
		"deviceVersion":"16.7.11",
		"platform":"WEB_IOS",
		"device":"1",
		"countryCode":"CN",
		"appVersion":"5.67.0",
		"locale":"zh-CN",
		"deviceId":"92013EC5-A07F-4B54-A2C1-5E75D197A681"
	},
	"pd":{
		"code":"CN1226428222",
		"countryCode":"CN",
		"languageCode":"CN",
		"source":1
	},
	"nv":"2",
	"nt":"1750299962170",
	"nn":"joejBkQVWsCQtTIjzgb6BzOzh",
	"nd":"e8c6464a161d941"
}